Workbook

Sheet Investors
A1: InvestorID | B1: FullName | C1: Email | D1: PhoneNumber | E1: PANNumber | F1: DateofBirth | G1: City | H1: State | I1: RegistrationDate
A2: 1001 | B2: Kumar Utkarsh | C2: utkarsh@gmail.com | D2: 9123195802 | E2: ABCDE1234F | F2: 38283 | G2: Jamshedpur | H2: Jharkhand | I2: 46237
A3: 1002 | B3: Rahul Sharma | C3: rahul@gmail.com | D3: 9876543211 | E3: BCDEF2345G | F3: 35930 | G3: Delhi | H3: Delhi | I3: 46237
A4: 1003 | B4: Aman Verma | C4: aman@gmail.com | D4: 9876543212 | E4: CDEFG3456H | F4: 36392 | G4: Lucknow | H4: Uttar Pradesh | I4: 46237
A5: 1004 | B5: Priya Singh | C5: priya@gmail.com | D5: 9876543213 | E5: DEFGH4567J | F5: 36535 | G5: Mumbai | H5: Maharashtra | I5: 46237
A6: 1005 | B6: Sneha Gupta | C6: sneha@gmail.com | D6: 9876543214 | E6: EFGHI5678K | F6: 35514 | G6: Kolkata | H6: West Bengal | I6: 46237
A7: 1006 | B7: Rohit Kumar | C7: rohit@gmail.com | D7: 9876543215 | E7: FGHIJ6789L | F7: 35374 | G7: Patna | H7: Bihar | I7: 46237
A8: 1007 | B8: Anjali Mishra | C8: anjali@gmail.com | D8: 9876543216 | E8: GHIJK7890M | F8: 37060 | G8: Bhopal | H8: Madhya Pradesh | I8: 46237
A9: 1008 | B9: Keshav Anand | C9: keshav@gmail.com | D9: 9876543217 | E9: HIJKL8901N | F9: 37602 | G9: Kanpur | H9: Uttar Pradesh | I9: 46237
A10: 1009 | B10: Vivek Sinha | C10: vivek@gmail.com | D10: 9876543218 | E10: IJKLM9012P | F10: 34972 | G10: Ranchi | H10: Jharkhand | I10: 46237
A11: 1010 | B11: Neha Kapoor | C11: neha@gmail.com | D11: 9876543219 | E11: JKLMN0123Q | F11: 36258 | G11: Chandigarh | H11: Chandigarh | I11: 46237

Sheet AMC
A1: AMCID | B1: AMCName | C1: Headquarters | D1: FoundedYear | E1: Website
A2: 101 | B2: SBI Mutual Fund | C2: Mumbai | D2: 1987 | E2: sbimf.com
A3: 102 | B3: HDFC Mutual Fund | C3: Mumbai | D3: 1999 | E3: hdfcfund.com
A4: 103 | B4: ICICI Prudential Mutual Fund | C4: Mumbai | D4: 1993 | E4: icicipruamc.com
A5: 104 | B5: Nippon India Mutual Fund | C5: Mumbai | D5: 1995 | E5: nipponindiamf.com
A6: 105 | B6: Axis Mutual Fund | C6: Mumbai | D6: 2009 | E6: axismf.com

Sheet FundCategory
A1: CategoryID | B1: CategoryName | C1: RiskLevel | D1: Description
A2: 1 | B2: Equity | C2: High | D2: Invests mainly in stocks
A3: 2 | B3: Debt | C3: Low | D3: Invests in fixed income securities
A4: 3 | B4: Hybrid | C4: Medium | D4: Mix of equity and debt
A5: 4 | B5: Index | C5: Medium | D5: Tracks a market index
A6: 5 | B6: ELSS | C6: High | D6: Tax saving mutual fund

Sheet Pivot_Category
A3: Row Labels | B3: Sum of Total Investment
A4: Debt | B4: 12000
A5: ELSS | B5: 3000
A6: Equity | B6: 39000
A7: Hybrid | B7: 22000
A8: Index | B8: 5000
A9: Grand Total | B9: 81000

Sheet MutualFunds
A1: FundID | B1: FundName | C1: AMCID | D1: CategoryID | E1: LaunchDate | F1: MinimumInvestment | G1: ExpenseRatio | H1: ExitLoad | I1: CurrentNAV | J1: Total Investment | K1: Category Name
A2: 2001 | B2: SBI Bluechip Fund | C2: 101 | D2: 1 | E2: 40223 | F2: 500 | G2: 0.85 | H2: 1 | I2: 95.45 | J2: =SUMIF(Transactions!C:C,A2,Transactions!E:E) -> 5000 | K2: =VLOOKUP(D2,FundCategory!A:B,2,FALSE) -> Equity
A3: 2002 | B3: SBI Small Cap Fund | C3: 101 | D3: 1 | E3: 40071 | F3: 500 | G3: 0.95 | H3: 1 | I3: 178.6 | J3: =SUMIF(Transactions!C:C,A3,Transactions!E:E) -> 8000 | K3: =VLOOKUP(D3,FundCategory!A:B,2,FALSE) -> Equity
A4: 2003 | B4: HDFC Flexi Cap Fund | C4: 102 | D4: 1 | E4: 34700 | F4: 100 | G4: 0.8 | H4: 1 | I4: 1456.2 | J4: =SUMIF(Transactions!C:C,A4,Transactions!E:E) -> 10000 | K4: =VLOOKUP(D4,FundCategory!A:B,2,FALSE) -> Equity
A5: 2004 | B5: ICICI Prudential Bluechip Fund | C5: 103 | D5: 1 | E5: 39587 | F5: 100 | G5: 0.89 | H5: 1 | I5: 112.75 | J5: =SUMIF(Transactions!C:C,A5,Transactions!E:E) -> 10000 | K5: =VLOOKUP(D5,FundCategory!A:B,2,FALSE) -> Equity
A6: 2005 | B6: Nippon India Large Cap Fund | C6: 104 | D6: 1 | E6: 39302 | F6: 500 | G6: 0.9 | H6: 1 | I6: 82.3 | J6: =SUMIF(Transactions!C:C,A6,Transactions!E:E) -> 6000 | K6: =VLOOKUP(D6,FundCategory!A:B,2,FALSE) -> Equity
A7: 2006 | B7: Axis ELSS Tax Saver Fund | C7: 105 | D7: 5 | E7: 40176 | F7: 500 | G7: 0.74 | H7: 0 | I7: 68.45 | J7: =SUMIF(Transactions!C:C,A7,Transactions!E:E) -> 3000 | K7: =VLOOKUP(D7,FundCategory!A:B,2,FALSE) -> ELSS
A8: 2007 | B8: HDFC Corporate Bond Fund | C8: 102 | D8: 2 | E8: 37325 | F8: 1000 | G8: 0.55 | H8: 0 | I8: 34.6 | J8: =SUMIF(Transactions!C:C,A8,Transactions!E:E) -> 12000 | K8: =VLOOKUP(D8,FundCategory!A:B,2,FALSE) -> Debt
A9: 2008 | B9: ICICI Prudential Balanced Advantage Fund | C9: 103 | D9: 3 | E9: 39081 | F9: 1000 | G9: 0.72 | H9: 1 | I9: 58.95 | J9: =SUMIF(Transactions!C:C,A9,Transactions!E:E) -> 15000 | K9: =VLOOKUP(D9,FundCategory!A:B,2,FALSE) -> Hybrid
A10: 2009 | B10: Nippon India Index Fund | C10: 104 | D10: 4 | E10: 43556 | F10: 100 | G10: 0.3 | H10: 0 | I10: 24.5 | J10: =SUMIF(Transactions!C:C,A10,Transactions!E:E) -> 5000 | K10: =VLOOKUP(D10,FundCategory!A:B,2,FALSE) -> Index
A11: 2010 | B11: Axis Hybrid Fund | C11: 105 | D11: 3 | E11: 41233 | F11: 500 | G11: 0.68 | H11: 1 | I11: 41.8 | J11: =SUMIF(Transactions!C:C,A11,Transactions!E:E) -> 7000 | K11: =VLOOKUP(D11,FundCategory!A:B,2,FALSE) -> Hybrid

Sheet Pivot_Investor
A3: Row Labels | B3: Sum of Amount
A4: 1001 | B4: 5000
A5: 1002 | B5: 10000
A6: 1003 | B6: 3000
A7: 1004 | B7: 15000
A8: 1005 | B8: 8000
A9: 1006 | B9: 6000
A10: 1007 | B10: 12000
A11: 1008 | B11: 10000
A12: 1009 | B12: 5000
A13: 1010 | B13: 7000
A14: Grand Total | B14: 81000

Sheet Pivot_Fund
A3: Row Labels | B3: Sum of Amount
A4: 2001 | B4: 5000
A5: 2002 | B5: 8000
A6: 2003 | B6: 10000
A7: 2004 | B7: 10000
A8: 2005 | B8: 6000
A9: 2006 | B9: 3000
A10: 2007 | B10: 12000
A11: 2008 | B11: 15000
A12: 2009 | B12: 5000
A13: 2010 | B13: 7000
A14: Grand Total | B14: 81000

Sheet Pivot_TransactionType
A3: Row Labels | B3: Sum of Amount
A4: BUY | B4: 81000
A5: Grand Total | B5: 81000

Sheet Transactions
A1: TransactionID | B1: InvestorID | C1: FundID | D1: TransactionType | E1: Amount | F1: UnitsPurchased | G1: NAVAtTransaction | H1: TransactionDate
A2: 3001 | B2: 1001 | C2: 2001 | D2: BUY | E2: 5000 | F2: 52.38 | G2: 95.45 | H2: 46237
A3: 3002 | B3: 1002 | C3: 2003 | D3: BUY | E3: 10000 | F3: 6.87 | G3: 1456.2 | H3: 46237
A4: 3003 | B4: 1003 | C4: 2006 | D4: BUY | E4: 3000 | F4: 43.83 | G4: 68.45 | H4: 46237
A5: 3004 | B5: 1004 | C5: 2008 | D5: BUY | E5: 15000 | F5: 254.45 | G5: 58.95 | H5: 46237
A6: 3005 | B6: 1005 | C6: 2002 | D6: BUY | E6: 8000 | F6: 44.79 | G6: 178.6 | H6: 46237
A7: 3006 | B7: 1006 | C7: 2005 | D7: BUY | E7: 6000 | F7: 72.9 | G7: 82.3 | H7: 46237
A8: 3007 | B8: 1007 | C8: 2007 | D8: BUY | E8: 12000 | F8: 346.82 | G8: 34.6 | H8: 46237
A9: 3008 | B9: 1008 | C9: 2004 | D9: BUY | E9: 10000 | F9: 88.69 | G9: 112.75 | H9: 46237
A10: 3009 | B10: 1009 | C10: 2009 | D10: BUY | E10: 5000 | F10: 204.08 | G10: 24.5 | H10: 46237
A11: 3010 | B11: 1010 | C11: 2010 | D11: BUY | E11: 7000 | F11: 167.46 | G11: 41.8 | H11: 46237

Sheet Excel_Analysis
A1: KPI | B1: Value
A2: Total Investors | B2: =COUNTA(Investors!A2:A13) -> 10
A3: Total Mutual Funds | B3: =COUNTA(MutualFunds!A2:A11) -> 10
A4: Total Transactions | B4: =COUNTA(Transactions!A2:A11) -> 10
A5: Total Investment | B5: =SUM(Transactions!E2:E11) -> 81000
A6: Average Investment | B6: =AVERAGE(Transactions!E2:E11) -> 8100
A7: Highest Investment | B7: =MAX(Transactions!E2:E11) -> 15000

Sheet Investor_Analysis
A1: InvestorID | B1: Investor Name | C1: Total Investment | D1: Investment % | E1: Rank
A2: 1001 | B2: =VLOOKUP(A2,Investors!A:B,2,FALSE) -> Kumar Utkarsh | C2: =SUMIF(Transactions!B:B,A2,Transactions!E:E) -> 5000 | D2: =C2/$C$12 -> 0.061728395 | E2: =RANK(C2,$C$2:$C$11,0) -> 8
A3: 1002 | B3: =VLOOKUP(A3,Investors!A:B,2,FALSE) -> Rahul Sharma | C3: =SUMIF(Transactions!B:B,A3,Transactions!E:E) -> 10000 | D3: =C3/$C$12 -> 0.12345679 | E3: =RANK(C3,$C$2:$C$11,0) -> 3
A4: 1003 | B4: =VLOOKUP(A4,Investors!A:B,2,FALSE) -> Aman Verma | C4: =SUMIF(Transactions!B:B,A4,Transactions!E:E) -> 3000 | D4: =C4/$C$12 -> 0.037037037 | E4: =RANK(C4,$C$2:$C$11,0) -> 10
A5: 1004 | B5: =VLOOKUP(A5,Investors!A:B,2,FALSE) -> Priya Singh | C5: =SUMIF(Transactions!B:B,A5,Transactions!E:E) -> 15000 | D5: =C5/$C$12 -> 0.18518519 | E5: =RANK(C5,$C$2:$C$11,0) -> 1
A6: 1005 | B6: =VLOOKUP(A6,Investors!A:B,2,FALSE) -> Sneha Gupta | C6: =SUMIF(Transactions!B:B,A6,Transactions!E:E) -> 8000 | D6: =C6/$C$12 -> 0.098765432 | E6: =RANK(C6,$C$2:$C$11,0) -> 5
A7: 1006 | B7: =VLOOKUP(A7,Investors!A:B,2,FALSE) -> Rohit Kumar | C7: =SUMIF(Transactions!B:B,A7,Transactions!E:E) -> 6000 | D7: =C7/$C$12 -> 0.074074074 | E7: =RANK(C7,$C$2:$C$11,0) -> 7
A8: 1007 | B8: =VLOOKUP(A8,Investors!A:B,2,FALSE) -> Anjali Mishra | C8: =SUMIF(Transactions!B:B,A8,Transactions!E:E) -> 12000 | D8: =C8/$C$12 -> 0.14814815 | E8: =RANK(C8,$C$2:$C$11,0) -> 2
A9: 1008 | B9: =VLOOKUP(A9,Investors!A:B,2,FALSE) -> Keshav Anand | C9: =SUMIF(Transactions!B:B,A9,Transactions!E:E) -> 10000 | D9: =C9/$C$12 -> 0.12345679 | E9: =RANK(C9,$C$2:$C$11,0) -> 3
A10: 1009 | B10: =VLOOKUP(A10,Investors!A:B,2,FALSE) -> Vivek Sinha | C10: =SUMIF(Transactions!B:B,A10,Transactions!E:E) -> 5000 | D10: =C10/$C$12 -> 0.061728395 | E10: =RANK(C10,$C$2:$C$11,0) -> 8
A11: 1010 | B11: =VLOOKUP(A11,Investors!A:B,2,FALSE) -> Neha Kapoor | C11: =SUMIF(Transactions!B:B,A11,Transactions!E:E) -> 7000 | D11: =C11/$C$12 -> 0.086419753 | E11: =RANK(C11,$C$2:$C$11,0) -> 6
B12: Total Investment | C12: =SUM(C2:C11) -> 81000

Sheet Fund_Analysis
A1: FundID | B1: Fund Name | C1: Total Investment
A2: 2001 | B2: =VLOOKUP(A2,MutualFunds!A:B,2,FALSE) -> SBI Bluechip Fund | C2: =SUMIF(Transactions!C:C,A2,Transactions!E:E) -> 5000
A3: 2002 | B3: =VLOOKUP(A3,MutualFunds!A:B,2,FALSE) -> SBI Small Cap Fund | C3: =SUMIF(Transactions!C:C,A3,Transactions!E:E) -> 8000
A4: 2003 | B4: =VLOOKUP(A4,MutualFunds!A:B,2,FALSE) -> HDFC Flexi Cap Fund | C4: =SUMIF(Transactions!C:C,A4,Transactions!E:E) -> 10000
A5: 2004 | B5: =VLOOKUP(A5,MutualFunds!A:B,2,FALSE) -> ICICI Prudential Bluechip Fund | C5: =SUMIF(Transactions!C:C,A5,Transactions!E:E) -> 10000
A6: 2005 | B6: =VLOOKUP(A6,MutualFunds!A:B,2,FALSE) -> Nippon India Large Cap Fund | C6: =SUMIF(Transactions!C:C,A6,Transactions!E:E) -> 6000
A7: 2006 | B7: =VLOOKUP(A7,MutualFunds!A:B,2,FALSE) -> Axis ELSS Tax Saver Fund | C7: =SUMIF(Transactions!C:C,A7,Transactions!E:E) -> 3000
A8: 2007 | B8: =VLOOKUP(A8,MutualFunds!A:B,2,FALSE) -> HDFC Corporate Bond Fund | C8: =SUMIF(Transactions!C:C,A8,Transactions!E:E) -> 12000
A9: 2008 | B9: =VLOOKUP(A9,MutualFunds!A:B,2,FALSE) -> ICICI Prudential Balanced Advantage Fund | C9: =SUMIF(Transactions!C:C,A9,Transactions!E:E) -> 15000
A10: 2009 | B10: =VLOOKUP(A10,MutualFunds!A:B,2,FALSE) -> Nippon India Index Fund | C10: =SUMIF(Transactions!C:C,A10,Transactions!E:E) -> 5000
A11: 2010 | B11: =VLOOKUP(A11,MutualFunds!A:B,2,FALSE) -> Axis Hybrid Fund | C11: =SUMIF(Transactions!C:C,A11,Transactions!E:E) -> 7000
B12: Total Investment | C12: =SUM(C2:C11) -> 81000

Sheet AMC_Analysis
A1: AMCID | B1: AMC Name | C1: Total Investment
A2: 101 | B2: =VLOOKUP(A2,AMC!A:B,2,FALSE) -> SBI Mutual Fund | C2: =SUMIF(MutualFunds!C:C,A2,MutualFunds!J:J) -> 13000
A3: 102 | B3: =VLOOKUP(A3,AMC!A:B,2,FALSE) -> HDFC Mutual Fund | C3: =SUMIF(MutualFunds!C:C,A3,MutualFunds!J:J) -> 22000
A4: 103 | B4: =VLOOKUP(A4,AMC!A:B,2,FALSE) -> ICICI Prudential Mutual Fund | C4: =SUMIF(MutualFunds!C:C,A4,MutualFunds!J:J) -> 25000
A5: 104 | B5: =VLOOKUP(A5,AMC!A:B,2,FALSE) -> Nippon India Mutual Fund | C5: =SUMIF(MutualFunds!C:C,A5,MutualFunds!J:J) -> 11000
A6: 105 | B6: =VLOOKUP(A6,AMC!A:B,2,FALSE) -> Axis Mutual Fund | C6: =SUMIF(MutualFunds!C:C,A6,MutualFunds!J:J) -> 10000
A7: Total | C7: =SUM(C2:C6) -> 81000

Sheet Dashboard
A1: MUTUAL FUND MANAGEMENT SYSTEM
A3: Total Investors | B3: =Excel_Analysis!B2 -> 10 | C3: Total Mutual Funds | D3: =Excel_Analysis!B3 -> 10 | E3: Total Transactions | F3: =Excel_Analysis!B4 -> 10 | G3: Total Investment | H3: =Excel_Analysis!B5 -> 81000
A4: Average Investment | B4: =Excel_Analysis!B6 -> 8100 | C4: Highest Investment | D4: =Excel_Analysis!B7 -> 15000

Sheet Transaction_Analysis
A1: Transaction Type | B1: Number of Transactions | C1: Total Amount
A2: BUY | B2: =COUNTIF(Transactions!D:D,A2) -> 10 | C2: =SUM(Transactions!E2:E11) -> 81000
A3: SELL | B3: =COUNTIF(Transactions!D:D,A3) -> 0 | C3: =AVERAGE(Transactions!E2:E11) -> 8100
A4: SIP | B4: =COUNTIF(Transactions!D:D,A4) -> 0 | C4: =MAX(Transactions!E2:E11) -> 15000

Sheet Category_Analysis
A1: CategoryID | B1: Category Name | C1: Total Investment
A2: 1 | B2: =VLOOKUP(A2,FundCategory!A:B,2,FALSE) -> Equity | C2: =SUMIF(MutualFunds!D:D,A2,MutualFunds!J:J) -> 39000
A3: 2 | B3: =VLOOKUP(A3,FundCategory!A:B,2,FALSE) -> Debt | C3: =SUMIF(MutualFunds!D:D,A3,MutualFunds!J:J) -> 12000
A4: 3 | B4: =VLOOKUP(A4,FundCategory!A:B,2,FALSE) -> Hybrid | C4: =SUMIF(MutualFunds!D:D,A4,MutualFunds!J:J) -> 22000
A5: 4 | B5: =VLOOKUP(A5,FundCategory!A:B,2,FALSE) -> Index | C5: =SUMIF(MutualFunds!D:D,A5,MutualFunds!J:J) -> 5000
A6: 5 | B6: =VLOOKUP(A6,FundCategory!A:B,2,FALSE) -> ELSS | C6: =SUMIF(MutualFunds!D:D,A6,MutualFunds!J:J) -> 3000
A7: Total | C7: =SUM(C2:C6) -> 81000
